setup.py
Mohamads_First_Trial.egg-info/PKG-INFO
Mohamads_First_Trial.egg-info/SOURCES.txt
Mohamads_First_Trial.egg-info/dependency_links.txt
Mohamads_First_Trial.egg-info/not-zip-safe
Mohamads_First_Trial.egg-info/top_level.txt
distributions/Binomialdistribution.py
distributions/Gaussiandistribution.py
distributions/Generaldistribution.py
distributions/__init__.py